prompt_storm/__init__.py
prompt_storm/cli.py
prompt_storm/interfaces/service_interfaces.py
prompt_storm/models/config.py
prompt_storm/models/responses.py
prompt_storm/optimizer.py
prompt_storm/prompt_format.py
prompt_storm/services/batch_optimizer_service.py
prompt_storm/services/csv_service.py
prompt_storm/services/optimizer_service.py
prompt_storm/services/yaml_service.py
prompt_storm/utils/error_handler.py
prompt_storm/utils/logger.py
prompt_storm/utils/response_processor.py
prompt_storm-0.2.0.dist-info/LICENSE.txt
prompt_storm-0.2.0.dist-info/METADATA
prompt_storm-0.2.0.dist-info/WHEEL
prompt_storm-0.2.0.dist-info/entry_points.txt
prompt_storm-0.2.0.dist-info/RECORD
