Metadata-Version: 2.1
Name: prompt-storm
Version: 0.2.0
Summary: A project for prompt engineering and generation
Author: Your Name
Author-email: raphael.mansuy@gmail.com
Requires-Python: >=3.11,<4.0
Classifier: Programming Language :: Python :: 3
Classifier: Programming Language :: Python :: 3.11
Classifier: Programming Language :: Python :: 3.12
Classifier: Programming Language :: Python :: 3.13
Requires-Dist: boto3 (>=1.35.76,<2.0.0)
Requires-Dist: click (>=8.0.0)
Requires-Dist: litellm (>=1.0.0)
Requires-Dist: pydantic (>=2.0.0)
Requires-Dist: python-dotenv (>=1.0.0)
Requires-Dist: rich (>=10.0.0)
Requires-Dist: typer (>=0.9.0)
